ouch_connect-5.0.1.dist-info/METADATA
ouch_connect-5.0.1.dist-info/WHEEL
ouch_connect-5.0.1.dist-info/license_files/LICENSE
ouch_connect/ouch_connect.pyi
ouch_connect/__init__.py
ouch_connect/py.typed
ouch_connect/ouch_connect.abi3.so
ouch_connect-5.0.1.dist-info/RECORD
