Metadata-Version: 2.1
Name: ouch_connect
Version: 5.0.1
Classifier: Programming Language :: Rust
Classifier: Programming Language :: Python :: Implementation :: CPython
Classifier: Programming Language :: Python :: Implementation :: PyPy
Requires-Dist: links_connect >=0.1 ; extra == 'test'
Requires-Dist: pytest >=8.0 ; extra == 'test'
Provides-Extra: test
License-File: LICENSE
Summary: Python bindings for the OUCH protocol
Keywords: exchange,protocol
Author: Softstream <softstream.link@gmail.com>
Author-email: Softstream <softstream.link@gmail.com>
Requires-Python: >=3.11
Project-URL: Source Code, https://github.com/softstream-link/ouch
